EasyIsing/_Ising.py
EasyIsing/_IsingC.py
EasyIsing/_IsingCupy.py
EasyIsing/_IsingNumpy.py
EasyIsing/__init__.py
EasyIsing/ising.c
easyising-0.1.0.dist-info/METADATA
easyising-0.1.0.dist-info/WHEEL
easyising-0.1.0.dist-info/licenses/LICENSE
easyising-0.1.0.dist-info/RECORD
