Metadata-Version: 2.1
Name: EasyIsing
Version: 0.1.0
Summary: A small package that provides a simple Ising model simulation on a squared lattice with the Metropolis algorithm.
Project-URL: Homepage, https://github.com/hsguidi/EasyIsing
Project-URL: Bug Tracker, https://github.com/hsguidi/EasyIsing/issues
Author-email: "Henrique S. Guidi" <henriquesguidi@gmail.com>
License-File: LICENSE
Keywords: Ising,Lattice gas,Metropolis,Monte Carlo,Statistical mechanics
Classifier: Environment :: GPU :: NVIDIA CUDA :: 11.0
Classifier: Intended Audience :: Education
Classifier: Intended Audience :: Science/Research
Classifier: License :: OSI Approved :: MIT License
Classifier: Operating System :: POSIX :: Linux
Classifier: Programming Language :: C
Classifier: Programming Language :: Python :: 3.10
Classifier: Topic :: Scientific/Engineering
Classifier: Topic :: Software Development :: Libraries :: Python Modules
Requires-Python: >=3.10
Requires-Dist: numpy~=1.24
Requires-Dist: scipy~=1.9.0
Provides-Extra: cupy
Requires-Dist: cupy~=11.0.0; extra == 'cupy'
